get_nested/__init__.py
get_nested/core.py
get_nested-0.1.1.dist-info/METADATA
get_nested-0.1.1.dist-info/WHEEL
get_nested-0.1.1.dist-info/top_level.txt
get_nested-0.1.1.dist-info/RECORD
