Metadata-Version: 2.4
Name: get_nested
Version: 0.1.1
Summary: This is a package for demonstration purposes.
Author: temp try
Dynamic: author
Dynamic: description-content-type
Dynamic: summary
